[
   {
  "id": "official-uk-1",
  "name": "United Kingdom Server",
  "host": "35.197.218.209",
  "port": 26279,
  "type": "OFFICIAL",
  "flag": "🇬🇧",
  "configType": "SHADOWSOCKS",

  "method": "chacha20-ietf-poly1305",
  "password": "MZ79O3kFdDmBfd6ORxgUoL",

  "network": "tcp",
  "security": "none"
},

   {
  "id": "official-sg-1",
  "name": "Singapore Server 1",
  "host": "217.216.73.175",
  "port": 12685,
  "type": "OFFICIAL",
  "flag": "🇸🇬",
  "configType": "SHADOWSOCKS",

  "method": "2022-blake3-aes-256-gcm",
  "password": "7NS+7WByyZvYOSrRB9zFnOetPLIbqIMEb5o4ks5l5Os=:t+LB7iwWrvZPLahpUbttR3UjdKgUeHsb2u6PuceEiKI=",

  "network": "tcp",
  "security": "none"
   },

   {
  "id": "official-sg-2",
  "name": "Singapore Server 2",
  "host": "217.216.73.175",
  "port": 11264,
  "type": "OFFICIAL",
  "flag": "🇸🇬",
  "configType": "SHADOWSOCKS",

  "method": "2022-blake3-aes-256-gcm",
  "password": "uJ5UyT6I2K/czLBO8NJp2u9au56UV1jtHCoN/TGRvEU=:9j9H7wJpLkds6ibik9+RB3ylQt8qR2MmXwowaLHV2rA=",

  "network": "tcp",
  "security": "none"
   },

    {
  "id": "official-sg-3",
  "name": "Singapore Secure Server 1",
  "host": "217.216.73.175",
  "port": 30335,
  "type": "OFFICIAL",
  "flag": "🇸🇬",
  "configType": "VLESS",

  "uuid": "e0c9d512-cb94-4dff-a343-fa55949eb8f6",
  "encryption": "none",

  "network": "tcp",
  "security": "reality",

  "sni": "google.com",
  "publicKey": "n6eCdEDoKfJGFo9TkeqpqQ4a1YbO-FpU60-fMKcMfVg",
  "shortId": "75",
  "fingerprint": "chrome",

  "flow": ""
},
   
   {
  "id": "outline-jp-1",
  "name": "Japan Server 1",
  "host": "109.123.231.16",
  "port": 9647,
  "type": "OFFICIAL",
  "flag": "🇯🇵",
  "configType": "SHADOWSOCKS",

  "method": "chacha20-ietf-poly1305",
  "password": "wkS1lEWBDounqfzK4ZVUoA",

  "network": "tcp",
  "security": "none"
},

   {
  "id": "outline-jp-2",
  "name": "Japan Server 2",
  "host": "109.123.231.16",
  "port": 9647,
  "type": "OFFICIAL",
  "flag": "🇯🇵",
  "configType": "SHADOWSOCKS",

  "method": "chacha20-ietf-poly1305",
  "password": "wkS1lEWBDounqfzK4ZVUoA",

  "network": "tcp",
  "security": "none"
}

    
  ]
